{
  "template": "https://github.com/statisticsnorway/ssb-pypitemplate.git",
  "commit": "e4eee94f1d7d31406fd6ca71c2bad7a9a313d02b",
  "checkout": "2024.11.27",
  "context": {
    "cookiecutter": {
      "project_name": "arneso-pypitemplate-instance",
      "package_name": "arneso_pypitemplate_instance",
      "friendly_name": "Arneso Pypitemplate Instance",
      "copyright_owner": "Statistics Norway",
      "copyright_year": "2023",
      "author": "Arne Sørli",
      "email": "arne.sorli@ssb.no",
      "github_organization": "arneso-ssb",
      "version": "0.0.0",
      "license": "MIT",
      "development_status": "Development Status :: 4 - Beta",
      "code_quality_level": "High",
      "_copy_without_render": [
        "*.rst_t"
      ],
      "_jinja2_env_vars": {
        "lstrip_blocks": true,
        "trim_blocks": true
      },
      "_template": "https://github.com/statisticsnorway/ssb-pypitemplate.git"
    }
  },
  "directory": null
}
